det/__init__.py
det/det_response/analysis.py
det/det_response/presentation.py
det/det_response/semantic_distance.py
det/embeddings/adapters.py
det/embeddings/cache.py
det/embeddings/generator.py
det/helpers.py
det/llm/base.py
det/llm/llm_groq.py
det/llm/llm_langchain.py
det/llm/llm_ollama.py
det/llm/llm_openai.py
det/main.py
det/utils/__init__.py
det/utils/exceptions.py
det/utils/llm_handler.py
det/utils/prompt_manager.py
det-0.5.0.dist-info/LICENSE
det-0.5.0.dist-info/METADATA
det-0.5.0.dist-info/WHEEL
det-0.5.0.dist-info/entry_points.txt
det-0.5.0.dist-info/RECORD
