Metadata-Version: 2.1
Name: det
Version: 0.5.0
Summary: A framework to analyse the consistency of repeated requests to an LLM or LLM based Agent
Home-page: https://github.com/thompsonson/det
License: MIT
Author: Matthew Thompson
Author-email: thompsonson@gmail.com
Requires-Python: >=3.10,<4.0
Classifier: License :: OSI Approved :: MIT License
Classifier: Programming Language :: Python :: 3
Classifier: Programming Language :: Python :: 3.10
Classifier: Programming Language :: Python :: 3.11
Classifier: Programming Language :: Python :: 3.12
Requires-Dist: deepdiff (>=6.7.1,<7.0.0)
Requires-Dist: groq (>=0.11.0,<0.12.0)
Requires-Dist: langchain (>=0.1.12,<0.2.0)
Requires-Dist: langchain-community (>=0.0.29,<0.0.30)
Requires-Dist: langchain-openai (>=0.1.1,<0.2.0)
Requires-Dist: numpy (>=1.26.4,<2.0.0)
Requires-Dist: ollama (>=0.1.6,<0.2.0)
Requires-Dist: openai (>=1.12.0,<2.0.0)
Requires-Dist: rich (>=13.7.0,<14.0.0)
Requires-Dist: typer (>=0.9.0,<0.10.0)
Project-URL: Repository, https://github.com/thompsonson/det
